streamlit_calendar/__init__.py
streamlit_calendar/hatch_build.py
streamlit_calendar/frontend/.prettierrc
streamlit_calendar/frontend/index.html
streamlit_calendar/frontend/package-lock.json
streamlit_calendar/frontend/package.json
streamlit_calendar/frontend/tsconfig.json
streamlit_calendar/frontend/vite.config.ts
streamlit_calendar/frontend/build/bootstrap.min.css
streamlit_calendar/frontend/build/index.html
streamlit_calendar/frontend/build/assets/index-6F-Y1Bm-.js
streamlit_calendar/frontend/build/assets/index-CZ--LO09.css
streamlit_calendar/frontend/public/bootstrap.min.css
streamlit_calendar/frontend/src/index.tsx
streamlit_calendar/frontend/src/react-app-env.d.ts
streamlit_calendar/frontend/src/components/Calendar.tsx
streamlit_calendar/frontend/src/styles/Calendar.css
streamlit_calendar/frontend/src/types/Calendar.type.ts
streamlit_calendar_fork-1.3.2rc0.dist-info/METADATA
streamlit_calendar_fork-1.3.2rc0.dist-info/WHEEL
streamlit_calendar_fork-1.3.2rc0.dist-info/licenses/LICENSE
streamlit_calendar_fork-1.3.2rc0.dist-info/RECORD
