Metadata-Version: 2.4
Name: streamlit-calendar-fork
Version: 1.3.2rc0
Summary: 📆 A Streamlit component to show callendar using FullCalendar (https://fullcalendar.io)
Project-URL: Repository, https://github.com/im-perativa/streamlit-calendar
Project-URL: Homepage, https://github.com/im-perativa/streamlit-calendar
Project-URL: Issues, https://github.com/im-perativa/streamlit-calendar/issues
Author-email: Muhammad Luqman <im.imperativa@gmail.com>, Christian Tabedzki <35670232+tabedzki@users.noreply.github.com>
License: Apache-2.0
License-File: LICENSE
Keywords: streamlit,streamlit-component
Classifier: Development Status :: 4 - Beta
Classifier: Intended Audience :: Developers
Classifier: License :: OSI Approved :: Apache Software License
Classifier: Programming Language :: Python :: 3
Classifier: Programming Language :: Python :: 3.9
Classifier: Programming Language :: Python :: 3.10
Classifier: Programming Language :: Python :: 3.11
Classifier: Programming Language :: Python :: 3.12
Classifier: Programming Language :: Python :: 3.13
Classifier: Programming Language :: Python :: 3.14
Requires-Python: >=3.9
Requires-Dist: streamlit<2.0.0,>=1.12.0
Provides-Extra: dev
Requires-Dist: bandit>=1.7.5; extra == 'dev'
Requires-Dist: black>=22.6.0; extra == 'dev'
Requires-Dist: isort>=5.10.1; extra == 'dev'
Requires-Dist: watchdog==2.1.9; extra == 'dev'
